javier_vidal/__init__.py
javier_vidal-0.2.1.dist-info/LICENSE.txt
javier_vidal-0.2.1.dist-info/METADATA
javier_vidal-0.2.1.dist-info/WHEEL
javier_vidal-0.2.1.dist-info/top_level.txt
javier_vidal-0.2.1.dist-info/RECORD
