Metadata-Version: 2.1
Name: javier-vidal
Version: 0.2.1
Summary: Javier vidal
Home-page: UNKNOWN
Author: Javier vidal
Author-email: abascur2024@udec.cl
License: UNKNOWN
Platform: UNKNOWN
Classifier: Programming Language :: Python :: 3
Classifier: License :: OSI Approved :: MIT License
Classifier: Operating System :: OS Independent
License-File: LICENSE.txt
